statified_nies/__init__.py
statified_nies/transformations.py
statified_nies-0.1.3.dist-info/LICENSE
statified_nies-0.1.3.dist-info/WHEEL
statified_nies-0.1.3.dist-info/METADATA
statified_nies-0.1.3.dist-info/RECORD
