Metadata-Version: 2.1
Name: statified_nies
Version: 0.1.3
Summary: A hierarchical review app using Streamlit
Home-page: https://github.com/niesfutbol/statified_nies
Author: NIES
Author-email: nepo@nies.futbol
Requires-Python: >=3.9
Classifier: License :: OSI Approved :: GNU General Public License v3 or later (GPLv3+)
